colinker/__init__.py
colinker/colinker.py
colinker/mn_builder.py
colinker/monitor.py
colinker/run_colinker.py
colinker/example/__init__.py
colinker/example/com_emu/Untitled-1
colinker/example/com_emu/__init__.py
colinker/example/com_emu/hosts.json
colinker/example/com_emu/pv_1_2_mn.py
colinker/example/com_emu/pv_m_n_bess_mn.py
colinker/example/com_emu/pv_m_n_bess_mn_vpn.py
colinker/example/com_emu/test1.py
colinker/example/com_emu/test_2.py
colinker/example/com_emu/veth_1.py
colinker/example/com_emu/vpn_1.py
colinker/example/com_emu/svg/cig.svg
colinker/example/com_emu/svg/cig_r.svg
colinker/example/emec_emu/__init__.py
colinker/example/emec_emu/pv_1_2_bess/__init__.py
colinker/example/emec_emu/pv_1_2_bess/config.json
colinker/example/emec_emu/pv_1_2_bess/config_controller.json
colinker/example/emec_emu/pv_1_2_bess/config_devices.json
colinker/example/emec_emu/pv_1_2_bess/config_devices_mn.json
colinker/example/emec_emu/pv_1_2_bess/config_simulator.json
colinker/example/emec_emu/pv_1_2_bess/daesolver_ini.c
colinker/example/emec_emu/pv_1_2_bess/daesolver_ini.h
colinker/example/emec_emu/pv_1_2_bess/daesolver_run.c
colinker/example/emec_emu/pv_1_2_bess/daesolver_run.h
colinker/example/emec_emu/pv_1_2_bess/dict_modbus.py
colinker/example/emec_emu/pv_1_2_bess/emulator.py
colinker/example/emec_emu/pv_1_2_bess/makeconfigs.py
colinker/example/emec_emu/pv_1_2_bess/pv_1_2.py
colinker/example/emec_emu/pv_1_2_bess/pv_1_2_ini.py
colinker/example/emec_emu/pv_1_2_bess/pv_1_2_xy_0.json
colinker/example/emec_emu/pv_1_2_bess/pv_mn_bess_builder.py
colinker/example/emec_emu/pv_1_2_bess/solver_ini.c
colinker/example/emec_emu/pv_1_2_bess/solver_run.c
colinker/example/emec_emu/pv_1_2_bess/vrt_state.py
colinker/example/emec_emu/pv_1_2_bess/xy_0.json
colinker/example/emec_emu/pv_1_2_bess/Release/daesolver_ini.obj
colinker/example/emec_emu/pv_1_2_bess/Release/daesolver_run.obj
colinker/example/emec_emu/pv_1_2_bess/Release/solver_ini.obj
colinker-0.2.0.dist-info/LICENSE
colinker-0.2.0.dist-info/WHEEL
colinker-0.2.0.dist-info/METADATA
colinker-0.2.0.dist-info/RECORD
