Metadata-Version: 2.1
Name: colinker
Version: 0.2.0
Summary: COCOON linker
Author-email: Juan Manuel Mauricio <jmmauricio@us.es>
Maintainer-email: Juan Manuel Mauricio <jmmauricio@us.es>
Requires-Dist: coverage ; extra == "dev"
Requires-Dist: mypy ; extra == "dev"
Requires-Dist: pytest ; extra == "dev"
Project-URL: bugs, https://github.com/jmmauricio/colinker/issues
Project-URL: changelog, https://github.com/jmmauricio/colinker/blob/master/changelog.md
Project-URL: homepage, https://github.com/jmmauricio/colinker
Provides-Extra: dev
